<?xml version="1.0" encoding="UTF-8"?>
<!DOCTYPE hibernate-mapping PUBLIC 
	"-//Hibernate/Hibernate Mapping DTD 3.0//EN" 
	"http://hibernate.sourceforge.net/hibernate-mapping-3.0.dtd">

<hibernate-mapping package="my.webapp.workman.bo">
	<class name="DateEvent" table="DATE_EVENT">
		<id name="id" column="id"><generator class="native" /></id>
		<property name="deleted" column="deleted" />
		<property name="lastUpdateTs" column="last_update_ts" />
		<property name="lastUpdateUr" column="last_update_ur" />

		<property name="date" column="DATE" />
		<property name="event" column="EVENT" />
	</class>
</hibernate-mapping>
